modestpy/__init__.py
modestpy/estimation.py
modestpy/loginit.py
modestpy/estim/__init__.py
modestpy/estim/error.py
modestpy/estim/estpar.py
modestpy/estim/make_param_file.py
modestpy/estim/plots.py
modestpy/estim/ga/__init__.py
modestpy/estim/ga/algorithm.py
modestpy/estim/ga/ga.py
modestpy/estim/ga/individual.py
modestpy/estim/ga/population.py
modestpy/estim/ga_parallel/__init__.py
modestpy/estim/ga_parallel/ga_parallel.py
modestpy/estim/ps/__init__.py
modestpy/estim/ps/ps.py
modestpy/estim/scipy/__init__.py
modestpy/estim/scipy/scipy.py
modestpy/fmi/__init__.py
modestpy/fmi/compiler.py
modestpy/fmi/fmpy_test.py
modestpy/fmi/fmpy_warning_example.py
modestpy/fmi/model.py
modestpy/fmi/model_pyfmi.py
modestpy/test/__init__.py
modestpy/test/run.py
modestpy/test/test_estimation.py
modestpy/test/test_fmpy.py
modestpy/test/test_ga.py
modestpy/test/test_ga_parallel.py
modestpy/test/test_ps.py
modestpy/test/test_scipy.py
modestpy/test/test_utilities.py
modestpy/test/resources/simple2R1C/Simple2R1C.mo
modestpy/test/resources/simple2R1C/Simple2R1C_linux64.fmu
modestpy/test/resources/simple2R1C/Simple2R1C_win32.fmu
modestpy/test/resources/simple2R1C/Simple2R1C_win64.fmu
modestpy/test/resources/simple2R1C/est.json
modestpy/test/resources/simple2R1C/inputs.csv
modestpy/test/resources/simple2R1C/known.json
modestpy/test/resources/simple2R1C/parameters.csv
modestpy/test/resources/simple2R1C/result.csv
modestpy/test/resources/simple2R1C_ic/Simple2R1C_ic.mo
modestpy/test/resources/simple2R1C_ic/Simple2R1C_ic_linux64.fmu
modestpy/test/resources/simple2R1C_ic/Simple2R1C_ic_win32.fmu
modestpy/test/resources/simple2R1C_ic/Simple2R1C_ic_win64.fmu
modestpy/test/resources/simple2R1C_ic/est.json
modestpy/test/resources/simple2R1C_ic/inputs.csv
modestpy/test/resources/simple2R1C_ic/known.json
modestpy/test/resources/simple2R1C_ic/result.csv
modestpy/test/resources/simple2R1C_ic/true_parameters.csv
modestpy/utilities/__init__.py
modestpy/utilities/delete_logs.py
modestpy/utilities/figures.py
modestpy-0.1.1.dist-info/LICENSE
modestpy-0.1.1.dist-info/METADATA
modestpy-0.1.1.dist-info/WHEEL
modestpy-0.1.1.dist-info/top_level.txt
modestpy-0.1.1.dist-info/RECORD
