Metadata-Version: 2.1
Name: modestpy
Version: 0.1.1
Summary: FMI-compliant model identification package
Home-page: https://github.com/sdu-cfei/modest-py
Author: Krzysztof Arendt, Center for Energy Informatics SDU
Author-email: krzysztof.arendt@gmail.com, veje@mmmi.sdu.dk
License: BSD
Keywords: fmi fmu optimization model identification estimation
Platform: Windows
Platform: Linux
Classifier: Programming Language :: Python :: 3
Requires-Dist: fmpy
Requires-Dist: matplotlib
Requires-Dist: modestga
Requires-Dist: numpy
Requires-Dist: pandas
Requires-Dist: pyDOE
Requires-Dist: scipy
